bve_cz_conventional.py
bve_cz_conventional-0.1.2.dev0.dist-info/LICENSE
bve_cz_conventional-0.1.2.dev0.dist-info/METADATA
bve_cz_conventional-0.1.2.dev0.dist-info/WHEEL
bve_cz_conventional-0.1.2.dev0.dist-info/entry_points.txt
bve_cz_conventional-0.1.2.dev0.dist-info/RECORD
