Metadata-Version: 2.1
Name: bve_cz_conventional
Version: 0.1.2.dev0
Summary: Breve flavored commitizen-tools/commitizen extension with gitmoji and i18n.
License: MIT
Author: atlasfoo
Author-email: atlasfoo@brevetech.com
Requires-Python: >=3.9,<4.0
Classifier: License :: OSI Approved :: MIT License
Classifier: Programming Language :: Python :: 3
Classifier: Programming Language :: Python :: 3.9
Classifier: Programming Language :: Python :: 3.10
Classifier: Programming Language :: Python :: 3.11
Classifier: Programming Language :: Python :: 3.12
Classifier: Programming Language :: Python :: 3.13
Requires-Dist: commitizen (>=3.29.1,<4.0.0)
